{
    "data": [
        {
            "id": 1612443577447026689,
            "text": "Dr. Charlotte Teschers hat im Rahmen ihrer Doktorarbeit bei Prof. Dr. Ryan Gilmour am Organisch-Chemischen Institut… https://t.co/8uJuNqk7Ew",
            "created_at": "Mon Jan 09 13:38:01 +0000 2023",
            "retweeters": [],
            "view_count": 3258,
            "retweet_count": 0,
            "favorite_count": 13,
            "quote_count": 1,
            "reply_count": 0,
            "lang": "de",
            "utc_timestamp": "2023-01-19 14:27:40.796279"
        }
    ]
}
